README.txt
setup.py
Products/__init__.py
Products.PloneSubscription.egg-info/PKG-INFO
Products.PloneSubscription.egg-info/SOURCES.txt
Products.PloneSubscription.egg-info/dependency_links.txt
Products.PloneSubscription.egg-info/entry_points.txt
Products.PloneSubscription.egg-info/namespace_packages.txt
Products.PloneSubscription.egg-info/not-zip-safe
Products.PloneSubscription.egg-info/requires.txt
Products.PloneSubscription.egg-info/top_level.txt
Products/PloneSubscription/ABOUT
Products/PloneSubscription/CHANGES
Products/PloneSubscription/LICENSE
Products/PloneSubscription/Log.py
Products/PloneSubscription/README.txt
Products/PloneSubscription/SubscriptionCatalog.py
Products/PloneSubscription/SubscriptionPermissions.py
Products/PloneSubscription/SubscriptionTool.py
Products/PloneSubscription/TESTED_WITH
Products/PloneSubscription/TODO
Products/PloneSubscription/__init__.py
Products/PloneSubscription/config.py
Products/PloneSubscription/configure.zcml
Products/PloneSubscription/product.txt
Products/PloneSubscription/profiles.zcml
Products/PloneSubscription/refresh.txt
Products/PloneSubscription/setuphandlers.py
Products/PloneSubscription/subscription_icon.gif
Products/PloneSubscription/version.txt
Products/PloneSubscription/Extensions/Install.py
Products/PloneSubscription/Extensions/MaintenanceToolbox.py
Products/PloneSubscription/Extensions/__init__.py
Products/PloneSubscription/content/AnonymousSubscriber.py
Products/PloneSubscription/content/ContentSubscription.py
Products/PloneSubscription/content/ExactSearchSubscription.py
Products/PloneSubscription/content/FolderSubscription.py
Products/PloneSubscription/content/GroupSubscriber.py
Products/PloneSubscription/content/KeywordsSubscription.py
Products/PloneSubscription/content/SubscriptionProvider.py
Products/PloneSubscription/content/SubscriptionTemplate.py
Products/PloneSubscription/content/TemplatesProvider.py
Products/PloneSubscription/content/UserSubscriber.py
Products/PloneSubscription/content/__init__.py
Products/PloneSubscription/content/schemata.py
Products/PloneSubscription/doc/FAQ
Products/PloneSubscription/doc/SCREENSHOTS
Products/PloneSubscription/doc/add_folder_subscription_for_group.png
Products/PloneSubscription/doc/add_grouped_subscriber.png
Products/PloneSubscription/doc/add_grouped_subscriber_form.png
Products/PloneSubscription/doc/add_subscription_for_group_tab.png
