Metadata-Version: 1.0
Name: Products.PloneSubscription
Version: 1.5.0
Summary: A Plone tool supporting different levels of subscription and notification.
Home-page: http://svn.plone.org/svn/collective/Products.PloneSubscription
Author: Alter Way Solutions
Author-email: support@alterway.fr
License: GPL
Keywords: plone subscription
Platform: UNKNOWN
Classifier: Programming Language :: Python
Classifier: Framework :: Plone
